database_connector/__init__.py
database_connector/constants.py
database_connector/rds_certificate.pem
database_connector/sagemaker.py
database_connector/snowflake_ds.py
database_connector/utils.py
squad_ds_utils/__init__.py
squad_ds_utils/exceptions.py
squad_ds_utils/parse.py
squad_ds_utils/recordings_fetcher.py
squad_ds_utils/secrets.py
squad_ds_utils-1.1.1.dist-info/METADATA
squad_ds_utils-1.1.1.dist-info/WHEEL
squad_ds_utils-1.1.1.dist-info/RECORD
