Metadata-Version: 2.3
Name: squad-ds-utils
Version: 1.1.1
Summary: 
Author: Ayush Shanker
Author-email: ayush+pypi@squadstack.com
Requires-Python: >=3.9,<4.0
Classifier: Programming Language :: Python :: 3
Classifier: Programming Language :: Python :: 3.9
Classifier: Programming Language :: Python :: 3.10
Classifier: Programming Language :: Python :: 3.11
Classifier: Programming Language :: Python :: 3.12
Classifier: Programming Language :: Python :: 3.13
Requires-Dist: SQLAlchemy (>=1.3.19,<2.0.0)
Requires-Dist: boto3 (>=1.35,<2.0)
Requires-Dist: cachetools (>=5.3.1,<6.0.0)
Requires-Dist: cryptography (>=43.0,<44.0)
Requires-Dist: keyring (>=23.11.0,<24.0.0)
Requires-Dist: psycopg2-binary (>=2.9.10,<3.0.0)
Requires-Dist: requests (>=2.32.0,<3.0.0)
Requires-Dist: snowflake-connector-python (>=3.12,<4.0)
Requires-Dist: zipp (==3.19.1)
